Workbook

Sheet  Bluedart 
A1: Category | B1: Parameter | C1: FY 2022-23 | D1: FY 2023-24 | E1: FY 2024-25 | I1: MALE | J1: FEMALE | K1: TOTAL(WORKERS) | L1: ratio of worker to employee
A2: Environmental | B2: Total Energy Consumption (MJ) | C2: 404549257 | D2: 763259501 | E2: 741317155 | F2: =AVERAGE(C2:E2) -> 6.363753e+08 | H2: FY 22-23 | I2: 8863 | J2: 185 | K2: =I2+J2 -> 9048 | L2: =K2/C12 -> 0.71843735
B3: Renewable Energy Consumption (MJ) | C3: 0 | D3: 51481440 | E3: 92296800 | F3: =AVERAGE(C3:E3) -> 47926080 | H3: FY23-24 | I3: 8908 | J3: 8707 | K3: =I3+J3 -> 17615 | L3: =K3/D12 -> 1.4045929
B4: Non-renewable Energy Consumption (MJ) | C4: 404549257 | D4: 711778061 | E4: 649020355 | F4: =AVERAGE(C4:E4) -> 5.8844922e+08 | H4: FY24-25 | I4: 8803 | J4: 232 | K4: =I4+J4 -> 9035 | L4: =K4/E12 -> 0.71124931
B5: Greenhouse Gas Emissions Scope 1 (MT CO2e) | C5: 166362 | D5: 147284 | E5: 170806 | F5: =AVERAGE(C5:E5) -> 161484
B6: Greenhouse Gas Emissions Scope 2 (MT CO2e) | C6: 16477 | D6: 15639 | E6: 15906 | F6: =AVERAGE(C6:E6) -> 16007.333
B7: Greenhouse Gas Emissions Scope 3 (MT CO2e) | C7: 253468 | D7: 284238 | E7: 309989 | F7: =AVERAGE(C7:E7) -> 282565
B8: Water Withdrawal (kL) | C8: 131350 | D8: 84477 | E8: 87154 | F8: =AVERAGE(C8:E8) -> 100993.67
B9: Waste Generated (Metric Tonnes) | C9: 20.52 | D9: 17.18 | E9: 234.67 | F9: =AVERAGE(C9:E9) -> 90.79
B10: E-waste Generated (Metric Tonnes) | C10: 18.31 | D10: 13.62 | E10: 13.62 | F10: =AVERAGE(C10:E10) -> 15.183333
A11: total | F11: =AVERAGE(C11:E11) -> #DIV/0!
A12: Social | B12: Total Employees | C12: 12594 | D12: 12541 | E12: 12703 | F12: =AVERAGE(C12:E12) -> 12612.667
B13: Permanent Male Employees | C13: 11940 | D13: 11867 | E13: 12004 | F13: =AVERAGE(C13:E13) -> 11937
B14: Permanent Female Employees | C14: 654 | D14: 674 | E14: 699 | F14: =AVERAGE(C14:E14) -> 675.66667
B15: Customer Complaints (Ratio) | C15: 0.03 | D15: 0.03 | E15: 0.07 | F15: =AVERAGE(C15:E15) -> 0.043333333
B16: Lost Time Injury Frequency Rate (Employees) | C16: Not available | D16: Not available | E16: Not available | F16: =AVERAGE(C16:E16) -> #DIV/0!
B17: Sexual Harassment Complaints Filed | C17: 2 | D17: 1 | E17: 1 | F17: =AVERAGE(C17:E17) -> 1.3333333
A18: Governance | B18: Board Diversity (% Women on Board) | C18: Not available | D18: Not available | E18: 0.3333 | F18: =AVERAGE(C18:E18) -> 0.3333
B19: Anti-Corruption Policy | C19: Yes | D19: Yes | E19: Yes | F19: =AVERAGE(C19:E19) -> #DIV/0!
B20: ISO Certifications | C20: ISO 9001, ISO 14001 | D20: ISO 9001, ISO 14001 | E20: ISO 9001, ISO 14001, ISO 27001 (planned) | F20: =AVERAGE(C20:E20) -> #DIV/0!
B21: Sustainability Committee | C21: Yes | D21: Yes | E21: Yes | F21: =AVERAGE(C21:E21) -> #DIV/0!
B22: Customer Complaint System (CARESS) | C22: Active | D22: Active | E22: Active | F22: =AVERAGE(C22:E22) -> #DIV/0!

Sheet  VRL 
A1: category | B1: Parameter | C1: FY 2022-23 | D1: FY 2023-24 | E1: FY 2024-25 | F1: average | H1: FY 2022-23 | I1: FY 2023-24 | J1: FY 2024-25
A2: Environmental | B2: Total Energy Consumption (GJ) | C2: 4175478.2 | D2: 3751227 | E2: 3710980.1 | F2: =AVERAGE(C2:E2) -> 3879228.4 | G2: ratio ofF/M | H2: =C15/C14 -> 0.012570112 | I2: =D15/D14 -> 0.012018215 | J2: =E15/E14 -> 0.013168087
B3: Renewable Energy Consumption (GJ) | C3: 19710 | D3: 51481 | E3: 92296 | F3: =AVERAGE(C3:E3) -> 54495.667 | G3: complaints pending to resolved ratio | H3: =839/30224 -> 0.027759397 | I3: =842/31678 -> 0.026579961 | J3: =767/89616 -> 0.0085587395
B4: Non-renewable Energy Consumption (GJ) | C4: 4155768.2 | D4: 3699746 | E4: 3618684.1 | F4: =AVERAGE(C4:E4) -> 3824732.8
B5: GHG Emissions Scope 1 (MT CO2e) | C5: 276436.62 | D5: 270094.39 | E5: 274255.01 | F5: =AVERAGE(C5:E5) -> 273595.34
B6: GHG Emissions Scope 2 (MT CO2e) | C6: 7923.8 | D6: 8624.19 | E6: 9418.15 | F6: =AVERAGE(C6:E6) -> 8655.38
B7: GHG Emissions Scope 3 (MT CO2e) | C7: 49758.59 | D7: 54018.88 | E7: 54851 | F7: =AVERAGE(C7:E7) -> 52876.157
B8: Water Withdrawal (kL) | C8: 406800 | D8: 398750 | E8: 42990 | F8: =AVERAGE(C8:E8) -> 282846.67
B9: Waste Generated (Metric Tonnes) | C9: 2481.59 | D9: 2480.79 | E9: 5058.93 | F9: =AVERAGE(C9:E9) -> 3340.4367
B10: E-waste Generated (Metric Tonnes) | C10: 0.8 | D10: 0.8 | E10: 0.9 | F10: =AVERAGE(C10:E10) -> 0.83333333
B11: Battery Waste (Metric Tonnes) | C11: 27.94 | D11: 20.43 | E11: 27.66 | F11: =AVERAGE(C11:E11) -> 25.343333
B12: Other Hazardous Waste (Metric Tonnes) | C12: 0.93 | D12: 6.43 | E12: 7.13 | F12: =AVERAGE(C12:E12) -> 4.83
A13: Social | B13: Total Employees | C13: 20219 | D13: 21557 | E13: 22236 | F13: =AVERAGE(C13:E13) -> 21337.333
B14: Permanent Male Employees | C14: 19968 | D14: 21301 | E14: 21947 | F14: =AVERAGE(C14:E14) -> 21072
B15: Permanent Female Employees | C15: 251 | D15: 256 | E15: 289 | F15: =AVERAGE(C15:E15) -> 265.33333
B16: Customer Complaints (Number) | C16: 31063 | D16: 32520 | E16: 90383 | F16: =AVERAGE(C16:E16) -> 51322
B17: Lost Time Injury Frequency Rate (LTIFR) | C17: Not reported | D17: 1.32 | E17: 0.83 | F17: =AVERAGE(C17:E17) -> 1.075
B18: Total Recordable Work-related Injuries | C18: 42 | D18: 69 | E18: 45 | F18: =AVERAGE(C18:E18) -> 52
B19: Employee Fatalities | C19: 38 | D19: 11 | E19: 20 | F19: =AVERAGE(C19:E19) -> 23
A20: Governance | B20: Board Diversity (% Women on Board) | C20: 0.1667 | D20: 0.1538 | E20: 0.0833 | F20: =AVERAGE(C20:E20) -> 0.1346
B21: Anti-Corruption Policy | C21: Yes | D21: Yes | E21: Yes
B22: Occupational Health & Safety System | C22: Yes | D22: Yes | E22: Yes
B23: ISO Certifications | C23: ISO 9001, ISO 14001 | D23: ISO 9001, ISO 14001 | E23: ISO 9001, ISO 14001, ISO 27001 planned

Sheet  Allcargo Gati
A1: Category | B1: Parameter | C1: FY 2022-23 | D1: FY 2023-24 | E1: FY 2024-25 | G1: average | J1: FY 2022-23 | K1: FY 2023-24 | L1: FY 2024-25
A2: Environmental | B2: Total Energy Consumption (GJ) | C2: 23247.31 | D2: 28280.62 | E2: 30703.07 | G2: =AVERAGE(C2:E2) -> 27410.333 | I2: ratio of workers to employees | J2: no workers employed | K2: =667/2735 -> 0.24387569 | L2: =843/2384 -> 0.35360738
B3: Renewable Energy Consumption (GJ) | C3: 615.27 | D3: 374.7 | E3: 2023.54 | G3: =AVERAGE(C3:E3) -> 1004.5033 | I3: customer complaint analysis
B4: Non-renewable Energy Consumption (GJ) | C4: 22632.04 | D4: 27905.92 | E4: 28679.53 | G4: =AVERAGE(C4:E4) -> 26405.83 | I4: total complaint received | J4: 15 | K4: 15 | L4: 8
B5: GHG Emissions Scope 1 (metric tonnes CO2e) | C5: 337.39 | D5: 390.96 | E5: 484.37 | G5: =AVERAGE(C5:E5) -> 404.24 | I5: pending | J5: 25 | K5: 6 | L5: 8
B6: GHG Emissions Scope 2 (metric tonnes CO2e) | C6: 3213.58 | D6: 6279 | E6: 4611.82 | G6: =AVERAGE(C6:E6) -> 4701.4667 | I6: resolved | J6: no proper disclosure | K6: 9 | L6: 0
B7: GHG Emissions Scope 3 (metric tonnes CO2e) | C7: 1749280.8 | D7: 871898.02 | E7: 910408.31 | G7: =AVERAGE(C7:E7) -> 1177195.7
B8: Water withdrawal (kL) | C8: Not Available | D8: Not Available | E8: Not Available | G8: =AVERAGE(C8:E8) -> #DIV/0!
B9: e-waste generated | C9: Not Available | D9: Not Available | E9: Not Available | G9: =AVERAGE(C9:E9) -> #DIV/0!
B10: Waste generation (metric tonnes) | C10: Not Available | D10: Not Available | E10: Not Available | G10: =AVERAGE(C10:E10) -> #DIV/0!
A11: Social | B11: Total Employees | C11: 3247 | D11: 537 | E11: 2384 | G11: =AVERAGE(C11:E11) -> 2056
B12: Permanent Employees Male | C12: 2822 | D12: 437 | E12: 2080 | G12: =AVERAGE(C12:E12) -> 1779.6667
B13: Permanent Employees Female | C13: 425 | D13: 100 | E13: 304 | G13: =AVERAGE(C13:E13) -> 276.33333
B14: Number of Complaints filed (various categories) | C14: Minor and few | D14: Minor and few | E14: Minor and few | G14: =AVERAGE(C14:E14) -> #DIV/0!
A15: Governance | B15: Board Diversity (Women on Board %) | C15: 0.1538 | D15: - | E15: 0.143 | G15: =AVERAGE(C15:E15) -> 0.1484
B16: Anti-corruption policies | C16: Available | D16: Available | E16: Available | G16: =AVERAGE(C16:E16) -> #DIV/0!
B17: Occupational Health & Safety Policy | C17: Implemented | D17: Implemented | E17: Implemented | G17: =AVERAGE(C17:E17) -> #DIV/0!
B18: Sustainability Committee | C18: Planned | D18: Planned | E18: Planned | G18: =AVERAGE(C18:E18) -> #DIV/0!
B19: ISO Certifications (Cybersecurity etc.) | C19: ISO 27001/270013 | D19: ISO 27001 and related | E19: ISO 27001:2022 | G19: =AVERAGE(C19:E19) -> #DIV/0!

Sheet  DEL -SOCIAL 
A1: category | B1: FY 2023-24 | C1: FY 2024-25 | D1: Details / Notes
A2: Total Employees and Workers | B2: 63790 | C2: 62064 | D2: Includes permanent and contractual workers.
A3: Permanent Employees (Male / Female) | B3: 18,326 / 1,658 | C3: 19,984 / 1,683 | D3: Slight increase in permanent workforce.
A4: Permanent Workers (Male / Female) | B4: 4,170 / 182 | C4: 4,352 / 182 | D4: Workers mainly involved in logistics operations.
A5: Sexual Harassment Complaints Filed | B5: 36 | C5: 50 | D5: Complaints registered under POSH Act; all addressed, 5 pending resolution in FY25.
A6: Sexual Harassment Complaints Upheld | B6: 29 | C6: 29 | D6: Confirmed cases after internal investigations.
A7: Working Conditions Complaints Filed | B7: 12 | C7: 79 | D7: Complaints raised regarding workplace environment.
A8: Health & Safety Complaints Filed | B8: 3 | C8: 4 | D8: Issues related to workplace safety.
A9: Employee Complaints (Overall) Filed | B9: 779 | C9: 1448 | D9: Includes all HR related complaints; all resolved by FY-end.
A10: Employee Health Programs | B10: - | C10: Ongoing | D10: Mental health trainings, safety drills, occupational health system.
A11: Training Hours - Health & Safety | B11: ~16,400 employees covered | C11: ~20,000 employees covered | D11: Training on POSH, anti-bribery, health and safety, etc.
A12: Inclusion Policies | B12: - | C12: Equal Employment Opportunity implemented | D12: Policy to prevent discrimination and promote diversity.
A13: Child Care Facilities | B13: - | C13: Rolled out to all workers | D13: Supports working parents at select facilities.

Sheet  DEL- GOV
A1: Metric / Initiative | B1: FY 2023-24 | C1: FY 2024-25 | D1: Details / Notes
A2: Board Diversity (Women %) | B2: 0.2222 | C2: 0.2222 | D2: Female representation on Board.
A3: Anti-Corruption Policies | B3: Yes | C3: Yes | D3: Strict code of conduct, anti-bribery and whistleblower policies.
A4: Whistleblower Complaints Filed | B4: 15 | C4: 7 | D4: Complaints from vendors/partners; all resolved except 1 in FY24.
A5: Corporate Social Responsibility (CSR) Spend (INR) | B5: 12842738 | C5: 14761269 | D5: Voluntary CSR spending on community programs.
A6: Compliance & Certifications | B6: ISO 9001, ISO 14001, ISO 45001, ISO 27001 | C6: Maintained & upgraded | D6: Integrated management systems for quality, environment, safety, and security.
A7: Stakeholder Engagement Programs | B7: Ongoing | C7: Ongoing | D7: Regular engagement with employees, customers, vendors, and communities.

Sheet  DEL- ENVI
A1: Metric / Initiative | B1: FY 2023-24 | C1: FY 2024-25 | D1: Details / Notes | E1: average
A2: Total Energy Consumption (MJ) | B2: 732291 | C2: 747243 | D2: Comprised of 2,937 MJ renewable (solar) and 729,354 MJ non-renewable in FY24; increased renewables to 4,773 MJ in FY25. | E2: =AVERAGE(B2:C2) -> 739767
A3: Renewable energy | B3: 2937330 | C3: 729353650 | E3: =AVERAGE(B3:C3) -> 366145490
A4: Non - Renewable energy | B4: 4773490 | C4: 742469610 | E4: =AVERAGE(B4:C4) -> 373621550
A5: GHG Emissions Scope 1 (MT CO2e) | B5: 156886 | C5: 186223 | D5: Greenhouse gases from owned sources including fuel combustion. | E5: =AVERAGE(B5:C5) -> 171554.5
A6: GHG Emissions Scope 2 (MT CO2e) | B6: 52669 | C6: 61144 | D6: Emissions from purchased electricity. | E6: =AVERAGE(B6:C6) -> 56906.5
A7: GHG Emissions Scope 3 (MT CO2e) | B7: 576188 | C7: 569766 | D7: Emissions from value chain and outsourced services. | E7: =AVERAGE(B7:C7) -> 572977
A8: Waste Generated (Metric Tonnes) | B8: 1899 | C8: 2480 | D8: Includes plastics (1,013 MT in FY24, 1,687 MT in FY25), e-waste, battery waste, etc. | E8: =AVERAGE(B8:C8) -> 2189.5
A9: e-waste generated | B9: 113.8 | C9: not avaible | D9: major increase due to asset upgrades, warehouse expansions and improved tracking, all e-waste is disposed off through authorized e-waste handlers, green certificates obtained after disposal
A10: Water Withdrawal (kL) | B10: 478418 | C10: 456540 | D10: Limited to human consumption with sensor taps to reduce wastage. | E10: =AVERAGE(B10:C10) -> 467479
A11: Solar Power Capacity (installed MW) | B11: 4.6 MW | C11: 7.0 MW | D11: Solar installations at 15 large facilities generating renewable energy. | E11: =AVERAGE(B11:C11) -> #DIV/0!
A12: Fleet Modernization | B12: - | C12: 1,600+ CNG/EV vehicles | D12: Deployment of clean energy vehicles for logistics to reduce emissions. | E12: =AVERAGE(B12:C12) -> #DIV/0!
A13: Energy Efficiency Initiatives | B13: Capex of 36.4 million INR | C13: Capex of 30.2 million INR | D13: Investments in fuel-efficient trucks, electric vehicles, rooftop solar. | E13: =AVERAGE(B13:C13) -> #DIV/0!
A14: Compliance & Certifications | B14: ISO 14001, ISO 45001, ISO 27001 | C14: Same | D14: Environmental, safety, and information security certifications maintained. | E14: =AVERAGE(B14:C14) -> #DIV/0!
A16: Renewable energy consumption (DEL not there)
A17: non renewable energy consumption (Del not there)
A18: e waste generated not there in Gati& DEL
A19: lost time frequency rate no there for (Gati&DEL)
A20: customer complaint ratio or number not there for (Gati & DEL)
A21: sexual harassment complaints filed not there for (VRL & Allc)
A22: sustainability commettee (not given in DEL & VRL)

Sheet  compiled 
A1: ENVIRONMENT | L1: SOCIAL | X1: GOVERNANCE
A2: BLUEDART | B2: CATEGORY | C2: FY22-23 | D2: FY23-24 | E2: FY24-25 | G2: weight (%) | I2: score | J2: Weighted Score | K2: Total Weighted Score | L2: BLUEDART | M2: CATEGORY | N2: FY22-23 | O2: FY23-24 | P2: FY24-25 | Q2: weights | R2: score | S2: Weight Scores | T2: Total Weighted Score | U2: comments | X2: BLUEDART | Y2: CATEGORY | Z2: FY22-23 | AA2: FY23-24 | AB2: FY24-25 | AC2: weights(%) | AD2: score | AE2: Weighted Score | AF2: Total Weight Score
B3: Energy consumed through Renewable sources | C3: 0 | D3: 51481440 | E3: 92296800 | F3: =AVERAGE(C3:E3) -> 47926080 | G3: 0.14285714 | I3: 4 | J3: =G3*I3 -> 0.57142857 | K3: =J3*Sheet1!$C$2 -> 0.23811429 | M3: Turnover rate of employees and workers | N3: =Sheet2!I19 -> 0.2753 | O3: =Sheet2!J19 -> 0.2824 | P3: =Sheet2!K19 -> 0.2815 | Q3: 0.16666667 | R3: 4 | S3: =R3*Q3 -> 0.66666667 | T3: =' compiled '!S3*Sheet1!$C$3 -> 0.2222 | U3: there Is a decent ratio between permanent workers and permanent employees | Y3: Board Diversity | AA3: 1/8 | AB3: 1/8 | AC3: 0.16666667 | AD3: 3 | AE3: =AC3*AD3 -> 0.5 | AF3: =AE3*Sheet1!$C$4 -> 0.125
B4: Energy consumed through Non-Renewable sources | C4: 404549257 | D4: 711778061 | E4: 649020355 | F4: =AVERAGE(C4:E4) -> 5.8844922e+08 | G4: 0.14285714 | I4: 2 | J4: =G4*I4 -> 0.28571429 | K4: =J4*Sheet1!$C$2 -> 0.11905714 | M4: Sexual Harassment Complaints Filed | N4: 2 | O4: 1 | P4: 1 | Q4: 0.16666667 | R4: 3 | S4: =R4*Q4 -> 0.5 | T4: =' compiled '!S4*Sheet1!$C$3 -> 0.16665 | Y4: Managerial Remuneration (median remuneration paid) | Z4: approx -1.3 crores | AA4: 1.35 crores | AB4: 1.5 crores | AC4: 0.16666667 | AD4: 2 | AE4: =AC4*AD4 -> 0.33333333 | AF4: =AE4*Sheet1!$C$4 -> 0.083333333
B5: GHG emission scope 1 | C5: 166362 | D5: 147284 | E5: 170806 | F5: =AVERAGE(C5:E5) -> 161484 | G5: 0.14285714 | I5: 3 | J5: =G5*I5 -> 0.42857143 | K5: =J5*Sheet1!$C$2 -> 0.17858571 | M5: Working Conditions Complaints Filed | O5: 2 | P5: 1 | Q5: 0.16666667 | R5: 4 | S5: =R5*Q5 -> 0.66666667 | T5: =' compiled '!S5*Sheet1!$C$3 -> 0.2222 | Y5: Employee Benefit Expenses | Z5: not stated | AA5: 53,271 lakhs | AB5: not specified | AC5: 0.16666667 | AD5: 3 | AE5: =AC5*AD5 -> 0.5 | AF5: =AE5*Sheet1!$C$4 -> 0.125
B6: GHG emission scope 2 | C6: 16477 | D6: 15639 | E6: 15906 | F6: =AVERAGE(C6:E6) -> 16007.333 | G6: 0.14285714 | I6: 3 | J6: =G6*I6 -> 0.42857143 | K6: =J6*Sheet1!$C$2 -> 0.17858571 | M6: Health & Safety Complaints Filed | O6: 0 | P6: 0 | Q6: 0.16666667 | R6: 3 | S6: =R6*Q6 -> 0.5 | T6: =' compiled '!S6*Sheet1!$C$3 -> 0.16665 | Y6: ISO certification compliance | Z6: ISO 9001, ISO 14001 | AA6: ISO 9001, ISO 14001 | AB6: ISO 9001, ISO 14001, ISO 27001 (planned) | AC6: 0.16666667 | AD6: 4 | AE6: =AC6*AD6 -> 0.66666667 | AF6: =AE6*Sheet1!$C$4 -> 0.16666667
B7: GHG emission scope 3 | C7: 253468 | D7: 284238 | E7: 309989 | F7: =AVERAGE(C7:E7) -> 282565 | G7: 0.14285714 | I7: 3 | J7: =G7*I7 -> 0.42857143 | K7: =J7*Sheet1!$C$2 -> 0.17858571 | M7: Diversity in Employment - employees | O7: 674/12541 - 5% | P7: 699/12703 - 5.5% | Q7: 0.16666667 | R7: 2 | S7: =R7*Q7 -> 0.33333333 | T7: =' compiled '!S7*Sheet1!$C$3 -> 0.1111 | Y7: Whistle Blower complaints (addressed to pending ratio) | Z7: 4 | AA7: 3 | AB7: 2 | AC7: 0.16666667 | AD7: 2.5 | AE7: =AC7*AD7 -> 0.41666667 | AF7: =AE7*Sheet1!$C$4 -> 0.10416667
B8: Water withdrawal | C8: 131350 | D8: 84477 | E8: 87154 | F8: =AVERAGE(C8:E8) -> 100993.67 | G8: 0.14285714 | I8: 3 | J8: =G8*I8 -> 0.42857143 | K8: =J8*Sheet1!$C$2 -> 0.17858571 | M8: Diversity in Employment - workers | O8: 201/8909-2.26% | P8: 232/9035 -2.57% | Q8: 0.16666667 | R8: 2 | S8: =R8*Q8 -> 0.33333333 | T8: =' compiled '!S8*Sheet1!$C$3 -> 0.1111 | Y8: CSR spending (average of 3 years) | Z8: not stated | AA8: 2081 lakhs | AB8: 1854 lakhs | AC8: 0.16666667 | AD8: 3 | AE8: =AC8*AD8 -> 0.5 | AF8: =AE8*Sheet1!$C$4 -> 0.125
B9: Waste generated | C9: 20.52 | D9: 17.18 | E9: 234.67 | F9: =AVERAGE(C9:E9) -> 90.79 | G9: 0.14285714 | I9: 4.5 | J9: =G9*I9 -> 0.64285714 | K9: =J9*Sheet1!$C$2 -> 0.26787857 | R9: =SUM(R3:R8) -> 18 | S9: =SUM(S3:S8) -> 3 | T9: =S9*Sheet1!C3 -> 0.9999 | AC9: =SUM(AC3:AC8) -> 1 | AD9: =SUM(AD3:AD8)/6 -> 2.9166667 | AE9: =SUM(AE3:AE8) -> 2.9166667 | AF9: =AE9*Sheet1!C4 -> 0.72916667
I10: =SUM(I3:I9)/7 -> 3.2142857 | J10: =SUM(J3:J9) -> 3.2142857 | K10: =J10*Sheet1!C2 -> 1.3393929 | N10: FY22-23 | O10: FY23-24 | P10: FY24-25
A11: VRL | B11: Energy consumed through Renewable sources | C11: 19710 | D11: 51481 | E11: 92296 | F11: =AVERAGE(C11:E11) -> 54495.667 | G11: 0.14285714 | I11: 2.5 | J11: =G11*I11 -> 0.35714286 | K11: =J11*Sheet1!$C$2 -> 0.14882143 | L11: VRL | M11: Turnover rate of employees and workers | N11: =30.72/100 -> 0.3072 | O11: =34.3/100 -> 0.343 | P11: =40.8/100 -> 0.408 | Q11: 0.16666667 | R11: 0 | S11: =Q11*R11 -> 0 | T11: =S11*Sheet1!$C$3 -> 0 | U11: there are no workers appointed | X11: VRL | Y11: Board Diversity | Z11: 1/12 | AA11: 2/13 | AB11: 1/12 | AC11: 0.16666667 | AD11: 2 | AE11: =AC11*AD11 -> 0.33333333 | AF11: =AE11*Sheet1!$C$4 -> 0.083333333
B12: Energy consumed through Non-Renewable sources | C12: 4155768.2 | D12: 3699746 | E12: 3618684.1 | F12: =AVERAGE(C12:E12) -> 3824732.8 | G12: 0.14285714 | I12: 1 | J12: =G12*I12 -> 0.14285714 | K12: =J12*Sheet1!$C$2 -> 0.059528571 | M12: Sexual Harassment Complaints Filed | N12: 0 | O12: 0 | P12: 0 | Q12: 0.16666667 | R12: 4.5 | S12: =Q12*R12 -> 0.75 | T12: =S12*Sheet1!$C$3 -> 0.249975 | Y12: Managerial Remuneration (median remuneration paid) | Z12: 1.70 crores | AA12: 1.55 crores | AB12: 1.70 crores | AC12: 0.16666667 | AD12: 2 | AE12: =AC12*AD12 -> 0.33333333 | AF12: =AE12*Sheet1!$C$4 -> 0.083333333
B13: GHG emission scope 1 | C13: 276436.62 | D13: 270094.39 | E13: 274255.01 | F13: =AVERAGE(C13:E13) -> 273595.34 | G13: 0.14285714 | I13: 1.5 | J13: =G13*I13 -> 0.21428571 | K13: =J13*Sheet1!$C$2 -> 0.089292857 | M13: Working Conditions Complaints Filed | N13: 28 | O13: 35 | P13: 12 | Q13: 0.16666667 | R13: 3 | S13: =Q13*R13 -> 0.5 | T13: =S13*Sheet1!$C$3 -> 0.16665 | Y13: Employee Benefit Expenses | Z13: 450 crores | AA13: 500crores | AB13: 550 crores | AC13: 0.16666667 | AD13: 3.5 | AE13: =AC13*AD13 -> 0.58333333 | AF13: =AE13*Sheet1!$C$4 -> 0.14583333
B14: GHG emission scope 2 | C14: 7923.8 | D14: 8624.19 | E14: 9418.15 | F14: =AVERAGE(C14:E14) -> 8655.38 | G14: 0.14285714 | I14: 2.5 | J14: =G14*I14 -> 0.35714286 | K14: =J14*Sheet1!$C$2 -> 0.14882143 | M14: Health & Safety Complaints Filed | N14: 8 | O14: 8 | P14: 4 | Q14: 0.16666667 | R14: 2 | S14: =Q14*R14 -> 0.33333333 | T14: =S14*Sheet1!$C$3 -> 0.1111 | Y14: ISO certification compliance | Z14: ISO 9001, ISO 14001 | AA14: ISO 9001, ISO 14001 | AB14: ISO 9001, ISO 14001, ISO 27001 planned | AC14: 0.16666667 | AD14: 4.5 | AE14: =AC14*AD14 -> 0.75 | AF14: =AE14*Sheet1!$C$4 -> 0.1875
B15: GHG emission scope 3 | C15: 49758.59 | D15: 54018.88 | E15: 54851 | F15: =AVERAGE(C15:E15) -> 52876.157 | G15: 0.14285714 | I15: 3 | J15: =G15*I15 -> 0.42857143 | K15: =J15*Sheet1!$C$2 -> 0.17858571 | M15: Diversity in Employment - employees | N15: 251/20219 | O15: 256/21557 | P15: 289/22236 | Q15: 0.16666667 | R15: 2 | S15: =Q15*R15 -> 0.33333333 | T15: =S15*Sheet1!$C$3 -> 0.1111 | Y15: Whistle Blower complaints (addressed to pending ratio) | Z15: 25 | AA15: 28 | AB15: 0 | AC15: 0.16666667 | AD15: 1 | AE15: =AC15*AD15 -> 0.16666667 | AF15: =AE15*Sheet1!$C$4 -> 0.041666667
B16: Water withdrawal | C16: 406800 | D16: 398750 | E16: 42990 | F16: =AVERAGE(C16:E16) -> 282846.67 | G16: 0.14285714 | I16: 3 | J16: =G16*I16 -> 0.42857143 | K16: =J16*Sheet1!$C$2 -> 0.17858571 | M16: Diversity in Employment - workers | N16: 0 | O16: 0 | P16: 0 | Q16: 0.16666667 | R16: 0 | S16: =Q16*R16 -> 0 | T16: =S16*Sheet1!$C$3 -> 0 | Y16: CSR spending (average of 3 years) | Z16: 252.75 lakhs | AA16: 376.33 lakhs | AB16: not specified | AC16: 0.16666667 | AD16: 3 | AE16: =AC16*AD16 -> 0.5 | AF16: =AE16*Sheet1!$C$4 -> 0.125
B17: Waste generated | C17: 2481.59 | D17: 2480.79 | E17: 5058.93 | F17: =AVERAGE(C17:E17) -> 3340.4367 | G17: 0.14285714 | I17: 3.5 | J17: =G17*I17 -> 0.5 | K17: =J17*Sheet1!$C$2 -> 0.20835 | R17: =SUM(R11:R16)/6 -> 1.9166667 | S17: =SUM(S11:S16) -> 1.9166667 | T17: =S17*Sheet1!C3 -> 0.638825 | AD17: =SUM(AD11:AD16)/6 -> 2.6666667 | AE17: =SUM(AE11:AE16) -> 2.6666667 | AF17: =AE17*Sheet1!C4 -> 0.66666667
I18: =SUM(I11:I17)/7 -> 2.4285714 | J18: =SUM(J11:J17) -> 2.4285714 | K18: =J18*Sheet1!C2 -> 1.0119857 | N18: FY22-23 | O18: FY23-24 | P18: FY24-25
A19: ALLCARGO | B19: Energy consumed through Renewable sources | C19: 615.27 | D19: 374.7 | E19: 2023.54 | F19: =AVERAGE(C19:E19) -> 1004.5033 | G19: 0.14285714 | I19: 1.5 | J19: =G19*I19 -> 0.21428571 | K19: =J19*Sheet1!$C$2 -> 0.089292857 | L19: ALLCARGO | M19: turnover rate of employees and workers | N19: =4.3/100 -> 0.043 | O19: =6/100 -> 0.06 | P19: =18/100 -> 0.18 | Q19: 0.16666667 | R19: 3.5 | S19: =R19*Q19 -> 0.58333333 | T19: =S19*Sheet1!$C$3 -> 0.194425
B20: Energy consumed through Non-Renewable sources | C20: 22632.04 | D20: 27905.92 | E20: 28679.53 | F20: =AVERAGE(C20:E20) -> 26405.83 | G20: 0.14285714 | I20: 2 | J20: =G20*I20 -> 0.28571429 | K20: =J20*Sheet1!$C$2 -> 0.11905714 | M20: Sexual Harassment Complaints Filed | N20: 1 | O20: 1 | P20: 2 | Q20: 0.16666667 | R20: 3.5 | S20: =R20*Q20 -> 0.58333333 | T20: =S20*Sheet1!$C$3 -> 0.194425 | X20: ALLCARGO GATI | Y20: Board Diversity | Z20: 1/7 | AA20: 1/8 | AB20: 1/8 | AC20: 0.16666667 | AD20: 2 | AE20: =AC20*AD20 -> 0.33333333 | AF20: =AE20*Sheet1!$C$4 -> 0.083333333
B21: GHG emission scope 1 | C21: 337.39 | D21: 390.96 | E21: 484.37 | F21: =AVERAGE(C21:E21) -> 404.24 | G21: 0.14285714 | I21: 4 | J21: =G21*I21 -> 0.57142857 | K21: =J21*Sheet1!$C$2 -> 0.23811429 | M21: Working Conditions Complaints Filed | N21: 0 | O21: 0 | P21: 0 | Q21: 0.16666667 | R21: 4.5 | S21: =R21*Q21 -> 0.75 | T21: =S21*Sheet1!$C$3 -> 0.249975 | Y21: Managerial Remuneration (median remuneration paid) | Z21: 678288 | AA21: not stated | AB21: 769548 | AC21: 0.16666667 | AD21: 2 | AE21: =AC21*AD21 -> 0.33333333 | AF21: =AE21*Sheet1!$C$4 -> 0.083333333
B22: GHG emission scope 2 | C22: 3213.58 | D22: 6279 | E22: 4611.82 | F22: =AVERAGE(C22:E22) -> 4701.4667 | G22: 0.14285714 | I22: 4.5 | J22: =G22*I22 -> 0.64285714 | K22: =J22*Sheet1!$C$2 -> 0.26787857 | M22: Health & Safety Complaints Filed | N22: 0 | O22: 0 | P22: 0 | Q22: 0.16666667 | R22: 4.5 | S22: =R22*Q22 -> 0.75 | T22: =S22*Sheet1!$C$3 -> 0.249975 | Y22: Employee Benefit Expenses | Z22: 314 lakhs | AA22: 274 lakhs | AB22: 17060 lakhs | AC22: 0.16666667 | AD22: 3 | AE22: =AC22*AD22 -> 0.5 | AF22: =AE22*Sheet1!$C$4 -> 0.125
B23: GHG emission scope 3 | C23: 1749280.8 | D23: 871898.02 | E23: 910408.31 | F23: =AVERAGE(C23:E23) -> 1177195.7 | G23: 0.14285714 | I23: 1 | J23: =G23*I23 -> 0.14285714 | K23: =J23*Sheet1!$C$2 -> 0.059528571 | M23: Diversity in Employment - employees | N23: 425/3247 | O23: 335/2735 | P23: 304/2384 | Q23: 0.16666667 | R23: 3 | S23: =R23*Q23 -> 0.5 | T23: =S23*Sheet1!$C$3 -> 0.16665 | Y23: ISO certification compliance | Z23: ISO 27001/270013 | AA23: ISO 27001 and related | AB23: ISO 27001:2022 | AC23: 0.16666667 | AD23: 4 | AE23: =AC23*AD23 -> 0.66666667 | AF23: =AE23*Sheet1!$C$4 -> 0.16666667
B24: Water withdrawal | C24: Not Available | D24: Not Available | E24: Not Available | G24: 0.14285714 | I24: 0 | J24: =G24*I24 -> 0 | K24: =J24*Sheet1!$C$2 -> 0 | M24: Diversity in Employment - workers | N24: 0 | O24: 93/667 | P24: 84/843 | Q24: 0.16666667 | R24: 3 | S24: =R24*Q24 -> 0.5 | T24: =S24*Sheet1!$C$3 -> 0.16665 | Y24: Whistle Blower complaints (addressed to pending ratio) | Z24: 0 | AA24: 0 | AB24: 0 | AC24: 0.16666667 | AD24: 4.5 | AE24: =AC24*AD24 -> 0.75 | AF24: =AE24*Sheet1!$C$4 -> 0.1875
B25: Waste generated | C25: Not Available | D25: Not Available | E25: Not Available | G25: 0.14285714 | J25: =SUM(J19:J24) -> 1.8571429 | K25: =J25*Sheet1!C2 -> 0.77387143 | R25: =SUM(R19:R24) -> 22 | S25: =SUM(S19:S24) -> 3.6666667 | T25: =S25*Sheet1!C3 -> 1.2221 | Y25: CSR spending (average of 3 years) | Z25: 12 lakhs | AA25: 13 lakhs | AB25: 13 lakhs | AC25: 0.16666667 | AD25: 2 | AE25: =AC25*AD25 -> 0.33333333 | AF25: =AE25*Sheet1!$C$4 -> 0.083333333
N26: FY22-23 | O26: FY23-24 | P26: FY24-25 | AD26: =SUM(AD20:AD25) -> 17.5 | AE26: =SUM(AE20:AE25) -> 2.9166667 | AF26: =AE26*Sheet1!C4 -> 0.72916667
A27: DELHIVERY | B27: Energy consumed through Renewable sources | D27: 2937330 | E27: 729353650 | F27: =AVERAGE(D27:E27) -> 366145490 | G27: 0.14285714 | I27: 2.5 | J27: =G27*I27 -> 0.35714286 | K27: =J27*Sheet1!$C$2 -> 0.14882143 | L27: DELHIVERY | M27: Turnover rate of employees and workers | N27: =Sheet2!I20 -> 0.635 | O27: =Sheet2!J20 -> 0.7393 | P27: =Sheet2!K20 -> 0.686 | Q27: 0.16666667 | R27: 2.5 | S27: =Q27*R27 -> 0.41666667 | T27: =S27*Sheet1!$C$3 -> 0.138875
B28: Energy consumed through Non-Renewable sources | D28: 4773490 | E28: 742469610 | F28: =AVERAGE(D28:E28) -> 373621550 | G28: 0.14285714 | I28: 1.5 | J28: =G28*I28 -> 0.21428571 | K28: =J28*Sheet1!$C$2 -> 0.089292857 | M28: Sexual Harassment Complaints Filed | O28: 36 | P28: 50 | Q28: 0.16666667 | R28: 1 | S28: =Q28*R28 -> 0.16666667 | T28: =S28*Sheet1!$C$3 -> 0.05555 | U28: Complaints registered under POSH Act; all addressed, 5 pending resolution in FY25. | X28: DELHIVERY | Y28: Board Diversity | AA28: 1/9 | AB28: 2/9 | AC28: 0.16666667 | AD28: 3 | AE28: =AC28*AD28 -> 0.5 | AF28: =AE28*Sheet1!$C$4 -> 0.125
B29: GHG emission scope 1 | D29: 156886 | E29: 186223 | F29: =AVERAGE(D29:E29) -> 171554.5 | G29: 0.14285714 | I29: 3 | J29: =G29*I29 -> 0.42857143 | K29: =J29*Sheet1!$C$2 -> 0.17858571 | M29: Working Conditions Complaints Filed | O29: 12 | P29: 79 | Q29: 0.16666667 | R29: 2 | S29: =Q29*R29 -> 0.33333333 | T29: =S29*Sheet1!$C$3 -> 0.1111 | U29: Complaints raised regarding workplace environment. | Y29: Managerial Remuneration (median remuneration paid) | AA29: 31021406 | AB29: 28620173 | AC29: 0.16666667 | AD29: 2.5 | AE29: =AC29*AD29 -> 0.41666667 | AF29: =AE29*Sheet1!$C$4 -> 0.10416667
B30: GHG emission scope 2 | D30: 52669 | E30: 61144 | F30: =AVERAGE(D30:E30) -> 56906.5 | G30: 0.14285714 | I30: 2 | J30: =G30*I30 -> 0.28571429 | K30: =J30*Sheet1!$C$2 -> 0.11905714 | M30: Health & Safety Complaints Filed | O30: 3 | P30: 4 | Q30: 0.16666667 | R30: 3 | S30: =Q30*R30 -> 0.5 | T30: =S30*Sheet1!$C$3 -> 0.16665 | U30: Issues related to workplace safety. | Y30: Employee Benefit Expenses | AA30: 15640(M) | AB30: 17651(M) | AC30: 0.16666667 | AD30: 3 | AE30: =AC30*AD30 -> 0.5 | AF30: =AE30*Sheet1!$C$4 -> 0.125
B31: GHG emission scope 3 | D31: 576188 | E31: 569766 | F31: =AVERAGE(D31:E31) -> 572977 | G31: 0.14285714 | I31: 2 | J31: =G31*I31 -> 0.28571429 | K31: =J31*Sheet1!$C$2 -> 0.11905714 | M31: Diversity in Employment - employees | O31: 1658/18326 | P31: 1683/19984 | Q31: 0.16666667 | R31: 3 | S31: =Q31*R31 -> 0.5 | T31: =S31*Sheet1!$C$3 -> 0.16665 | U31: Slight increase in permanent workforce. | Y31: ISO certification compliance | AA31: ISO 9001, ISO 14001, ISO 45001, ISO 27001 | AB31: Maintained & upgraded | AC31: 0.16666667 | AD31: 3 | AE31: =AC31*AD31 -> 0.5 | AF31: =AE31*Sheet1!$C$4 -> 0.125
B32: Water withdrawal | D32: 478418 | E32: 456540 | F32: =AVERAGE(D32:E32) -> 467479 | G32: 0.14285714 | I32: 2.5 | J32: =G32*I32 -> 0.35714286 | K32: =J32*Sheet1!$C$2 -> 0.14882143 | M32: Diversity in Employment - workers | O32: 182/4170 | P32: 182/4352 | Q32: 0.16666667 | R32: 3 | S32: =Q32*R32 -> 0.5 | T32: =S32*Sheet1!$C$3 -> 0.16665 | U32: Workers mainly involved in logistics operations. | Y32: Whistle Blower complaints (addressed to pending ratio) | AA32: 15 | AB32: 7 | AC32: 0.16666667 | AD32: 1 | AE32: =AC32*AD32 -> 0.16666667 | AF32: =AE32*Sheet1!$C$4 -> 0.041666667
B33: Waste generated | D33: 1899 | E33: 2480 | F33: =AVERAGE(D33:E33) -> 2189.5 | G33: 0.14285714 | I33: 3.5 | J33: =G33*I33 -> 0.5 | K33: =J33*Sheet1!$C$2 -> 0.20835 | Q33: =SUM(Q27:Q32) -> 1 | R33: =SUM(R27:R32)/6 -> 2.4166667 | S33: =SUM(S27:S32) -> 2.4166667 | T33: =S33*Sheet1!C3 -> 0.805475 | Y33: CSR spending (average of 3 years) | AA33: 12842738 | AB33: 14761269 | AC33: 0.16666667 | AD33: 3 | AE33: =AC33*AD33 -> 0.5 | AF33: =AE33*Sheet1!$C$4 -> 0.125
I34: =SUM(I27:I33) -> 17 | J34: =SUM(J27:J33) -> 2.4285714 | K34: =J34*Sheet1!C2 -> 1.0119857 | AD34: =SUM(AD28:AD33)/6 -> 2.5833333 | AE34: =SUM(AE28:AE33) -> 2.5833333 | AF34: =AE34*Sheet1!C4 -> 0.64583333
B41: Cummulative ESG Scores | C41: E | D41: S | E41: G | F41: Total ESG
B42: =A2 -> BLUEDART | C42: =K10 -> 1.3393929 | D42: =T9 -> 0.9999 | E42: =AF9 -> 0.72916667 | F42: =SUM(C42:E42) -> 3.0684595
B43: =A11 -> VRL | C43: =K18 -> 1.0119857 | D43: =T17 -> 0.638825 | E43: =AF17 -> 0.66666667 | F43: =SUM(C43:E43) -> 2.3174774
B44: =A19 -> ALLCARGO | C44: =K25 -> 0.77387143 | D44: =T25 -> 1.2221 | E44: =AF26 -> 0.72916667 | F44: =SUM(C44:E44) -> 2.7251381
B45: =A27 -> DELHIVERY | C45: =K34 -> 1.0119857 | D45: =T33 -> 0.805475 | E45: =AF34 -> 0.64583333 | F45: =SUM(C45:E45) -> 2.463294

Sheet Sheet1
B1: Weightage
B2: Environment | C2: 0.4167
B3: Social | C3: 0.3333
B4: Governance | C4: 0.25
C5: =SUM(C2:C4) -> 1
E7: Environment | G7: =100/7 -> 14.285714
G8: =G7/100 -> 0.14285714
E9: Social | G9: =100/6 -> 16.666667
G10: =G9/100 -> 0.16666667
E11: Governance | G11: =100/6 -> 16.666667
G12: =G11/100 -> 0.16666667

Sheet Sheet2
A1: year | B1: employee type | C1: turnover(male) | D1: turnover(female) | E1: turnover(total) | F1: (DELHIVERY) | H1: year | I1: employee type | J1: turnover(male) | K1: turnover(female) | L1: turnover(total) | M1: (VRL)
A2: FY22 | B2: permanent employee | C2: =33/100 -> 0.33 | D2: =36.82/100 -> 0.3682 | E2: =33.24/100 -> 0.3324 | H2: FY22 | I2: permanent employee | J2: =30.72/100 -> 0.3072 | K2: =8.81/100 -> 0.0881 | L2: =30.72/100 -> 0.3072
A3: FY23 | B3: permanent employee | C3: =41.93/100 -> 0.4193 | D3: =43.26/100 -> 0.4326 | E3: =42.02/100 -> 0.4202 | H3: FY23 | I3: permanent employee | J3: =34.3/100 -> 0.343 | K3: =9.61/100 -> 0.0961 | L3: =34.3/100 -> 0.343
A4: FY24 | B4: permanent employee | C4: =35.69/100 -> 0.3569 | D4: =45.15/100 -> 0.4515 | E4: =36.36/100 -> 0.3636 | H4: FY24 | I4: permanent employee | J4: =40.8/100 -> 0.408 | K4: =15.41/100 -> 0.1541 | L4: =40.8/100 -> 0.408
E5: =SUM(E2:E4)/3 -> 0.37206667 | L5: =SUM(L2:L4)/3 -> 0.35273333
A6: year | B6: employee type | C6: turnover(male) | D6: turnover(female) | E6: turnover(total) | H6: year | I6: employee type | J6: turnover(male) | K6: turnover(female) | L6: turnover(total) | M6: (GATI)
A7: FY22 | B7: permanent worker | C7: =30.55/100 -> 0.3055 | D7: =18.51/100 -> 0.1851 | E7: =30.26/100 -> 0.3026 | F7: =E2+E7 -> 0.635 | H7: FY22 | I7: permanent employee | J7: =4/100 -> 0.04 | K7: =6/100 -> 0.06 | L7: =4.3/100 -> 0.043
A8: FY23 | B8: permanent worker | C8: =31.75/100 -> 0.3175 | D8: =56.49/100 -> 0.5649 | E8: =31.91/100 -> 0.3191 | F8: =E3+E8 -> 0.7393 | H8: FY23 | I8: permanent employee | J8: =6/100 -> 0.06 | K8: =5/100 -> 0.05 | L8: =6/100 -> 0.06
A9: FY24 | B9: permanent worker | C9: =32.02/100 -> 0.3202 | D9: =33.82/100 -> 0.3382 | E9: =32.24/100 -> 0.3224 | F9: =E4+E9 -> 0.686 | H9: FY24 | I9: permanent employee | J9: =18/100 -> 0.18 | K9: =19/100 -> 0.19 | L9: =18/100 -> 0.18
E10: =SUM(E7:E9)/3 -> 0.3147 | L10: =SUM(L7:L9)/3 -> 0.094333333
A11: year | B11: employee type | C11: turnover(male) | D11: turnover(female) | E11: turnover(total) | F11: (BLUEDART)
A12: FY22 | B12: permanent employee | C12: =12.32/100 -> 0.1232 | D12: =16.35/100 -> 0.1635 | E12: =14.34/100 -> 0.1434 | I12: =(E5+E15+L5+L10)/4 -> 0.24015 | J12: empl
A13: FY23 | B13: permanent employee | C13: =11.57/100 -> 0.1157 | D13: =16.42/100 -> 0.1642 | E13: =13.99/100 -> 0.1399 | I13: =(E10+E20+L5+L10)/4 -> 0.22500833 | J13: worker
A14: FY24 | B14: permanent employee | C14: =12.06/100 -> 0.1206 | D14: =16.17/100 -> 0.1617 | E14: =14.11/100 -> 0.1411
E15: =SUM(E12:E14)/3 -> 0.14146667
A16: year | B16: employee type | C16: turnover(male) | D16: turnover(female) | E16: turnover(total) | I16: =(E4-E3)/E3 -> -0.13469776 | J16: =(C3-C2)/C2 -> 0.27060606
A17: FY22 | B17: permanent worker | C17: =12.08/100 -> 0.1208 | D17: =14.29/100 -> 0.1429 | E17: =13.19/100 -> 0.1319 | F17: =E12+E17 -> 0.2753 | I17: =(E3-E2)/E2 -> 0.26413959
A18: FY23 | B18: permanent worker | C18: =12.45/100 -> 0.1245 | D18: =16.06/100 -> 0.1606 | E18: =14.25/100 -> 0.1425 | F18: =E13+E18 -> 0.2824
A19: FY24 | B19: permanent worker | C19: =12.88/100 -> 0.1288 | D19: =15.21/100 -> 0.1521 | E19: =14.04/100 -> 0.1404 | F19: =E14+E19 -> 0.2815 | I19: =E12+E17 -> 0.2753 | J19: =E13+E18 -> 0.2824 | K19: =E14+E19 -> 0.2815
E20: =SUM(E17:E19)/3 -> 0.13826667 | I20: =E2+E7 -> 0.635 | J20: =E3+E8 -> 0.7393 | K20: =E4+E9 -> 0.686

Sheet Sheet3
B2: DOMAIN | C2: PARAMETERS | D2: WEIGHTAGE | E2: RATINGS | G2: DOMESTIC | H2: COMPANY | I2: RATINGS OUT OF FIVE
B3: ENVIRONMENT | C3: Energy consumed through Renewable sources | D3: 16.67 | E3: 2.5 | I3: ENVIRONMENT | J3: SOCIAL | K3: GOVERNANCE | L3: WEIGHTED SCORE
C4: Energy consumed through Non-Renewable sources | D4: 16.67 | E4: 1.5 | H4: BLUEDART LTD | I4: 3.21 | J4: 3.08 | K4: 2.92 | L4: 3.096
C5: GHG emission Scope -1 | D5: 16.67 | E5: 3 | H5: VRL LTD | I5: 2.43 | J5: 1.92 | K5: 2.67 | L5: 2.317
C6: GHG emission Scope -2 | D6: 16.67 | E6: 2 | H6: ALLCARGO GATI LTD | I6: 1.86 | J6: 3.67 | K6: 3.08 | L6: 2.767
C7: GHG emission Scope -3 | D7: 16.66 | E7: 2 | G7: INTERNATIONAL
C8: Water withdrawal | D8: 8.33 | E8: 2.5 | H8: UNITED PARCEL SERVICE | I8: =2.91/2 -> 1.455 | J8: =2.8/2 -> 1.4 | K8: =7.07/2 -> 3.535 | L8: =(I8*0.4167)+(J8*0.3333)+(K8*0.25) -> 1.9566685
C9: Waste generated | D9: 8.33 | E9: 3.5 | H9: FEDEX | I9: =4.57/2 -> 2.285 | J9: =2.5/2 -> 1.25 | K9: =7.9/2 -> 3.95 | L9: =(I9*0.4167)+(J9*0.3333)+(K9*0.25) -> 2.3562845
B10: AGGREGATE ENVIRONMENT SCORE | D10: 2.43 | H10: DHL GROUP | I10: =5.83/2 -> 2.915 | J10: =3.69/2 -> 1.845 | K10: =7.9/2 -> 3.95 | L10: =(I10*0.4167)+(J10*0.3333)+(K10*0.25) -> 2.817119
B11: SOCIAL | C11: Turnover rate of Employees and Workers | D11: 0.1667 | E11: 2.5 | H11: SF HOLDINGS | I11: =4.69/2 -> 2.345 | J11: =3.05/2 -> 1.525 | K11: =5.16/2 -> 2.58 | L11: =(I11*0.4167)+(J11*0.3333)+(K11*0.25) -> 2.130444
C12: Sexual Harassment complaints filed | D12: 0.1667 | E12: 1
C13: Working conditions related complaints | D13: 0.1667 | E13: 1 | G13: =SUM(D3:D9) -> 100
C14: Health and Safety related complaints | D14: 0.1667 | E14: 3
C15: Diversity in Employees | D15: 0.1667 | E15: 3 | H15: Delhivery | I15: domestic | J15: international
C16: Diversity in Workers | D16: 0.1667 | E16: 3 | G16: E | H16: =D10 -> 2.43 | I16: =AVERAGE(I4:I6) -> 2.5 | J16: =AVERAGE(I8:I11) -> 2.25
B17: AGGREGATE SOCIAL SCORE | D17: 2.42 | G17: S | H17: =D17 -> 2.42 | I17: =AVERAGE(J4:J6) -> 2.89 | J17: =AVERAGE(J8:J11) -> 1.505
B18: GOVERNANCE | C18: Board Diversity | D18: 0.1667 | E18: 2 | G18: G | H18: =D24 -> 2.58 | I18: =AVERAGE(K4:K6) -> 2.89 | J18: =AVERAGE(K8:K11) -> 3.50375
C19: Managerial Remuneration | D19: 0.1667 | E19: 2.5 | G19: Combined score | H19: 2.46 | I19: =AVERAGE(L4:L6) -> 2.7266667 | J19: =AVERAGE(L8:L11) -> 2.315129
C20: Employee Benefit Expenses | D20: 0.1667 | E20: 3
C21: ISO certification complaince | D21: 0.1667 | E21: 3
C22: Whistle Blower complaints | D22: 0.1667 | E22: 1
C23: CSR spending | D23: 0.1667 | E23: 3
B24: AGGREGATE GOVERNANCE SCORE | D24: 2.58
